[
  {
    "id": "survival_foundations::family_routines",
    "topic": "Family Preparedness and Daily Hardship Routines",
    "category": "survival_foundations",
    "subcategory": "household_preparedness",
    "tags": [
      "family",
      "routine",
      "children",
      "preparedness",
      "discipline"
    ],
    "summary_en": "Hardship becomes survivable when the household has repeatable routines. A boring schedule is a survival tool.",
    "summary_el": "Οι δυσκολίες γίνονται πιο διαχειρίσιμες όταν το νοικοκυριό έχει επαναλαμβανόμενες ρουτίνες. Ένα βαρετό πρόγραμμα είναι εργαλείο επιβίωσης.",
    "content_en": "A household under pressure bleeds strength through forgotten tasks: no one refills water, batteries are left on, trash accumulates, food is cooked without a plan, and medicine times drift. A daily routine prevents this. Morning should include health check, water check, sanitation check, weather/security check, and task assignment. Evening should focus on preparing for night: light discipline, charging priorities, tomorrow's water containers, secure clothing and shoes, and checking who needs medication, warmth, or reassurance. Children need truthful but age-appropriate explanations and stable tasks. In real use, this works best when it is reviewed often enough to stay familiar under stress and simple enough to apply without hesitation. Real usefulness increases when a method can be taught quickly, reviewed often, and adapted without losing its core logic. Under stress, people usually fall back to what is familiar, visible, and simple enough to repeat. The strongest knowledge is therefore not only accurate; it is also organized in a way that remains usable when memory, time, and patience are limited. Human reliability improves when people know what will happen next, what their role is, and how problems will be reviewed without humiliation. Much of resilience is emotional pacing: controlling rumor, lowering unnecessary surprise, and making sure tired people do not have to solve every problem at peak stress. Long-term strength also comes from using the topic as a system instead of as a one-time trick. That means checking how it behaves under repetition, shortage, bad weather, low light, fatigue, contamination risk, and handoff between different people. The best survival knowledge reduces decision overload by turning repeated tasks into visible routines with clear limits, reset points, and backup options. For Family Preparedness and Daily Hardship Routines, the advanced layer is legibility under stress: whether another person can understand, continue, and verify the system without needing the original author present. An important layer in Family Preparedness and Daily Hardship Routines is procedural: staging, timing, failure points, cleanup, follow-up, and what gets checked again after the first use. Systems improve when methods are clear enough for a tired second person to repeat. A deeper layer in Family Preparedness and Daily Hardship Routines comes from writing the method so another tired person can follow it in the dark with limited patience. That is a much harder standard than simply doing the task once successfully. Family Preparedness and Daily Hardship Routines becomes more durable when the method includes preparation, execution, inspection, recording, and reset rather than treating the task as finished the moment the visible action ends. Another polished lesson in Family Preparedness and Daily Hardship Routines is durability under interruption. A method is not really strong until it still works after noise, delay, tired hands, dim light, or a change of person halfway through.",
    "content_el": "Ένα πιεσμένο νοικοκυριό χάνει δύναμη από ξεχασμένες δουλειές: κανείς δεν ξαναγεμίζει νερό, οι μπαταρίες μένουν ανοιχτές, τα σκουπίδια συσσωρεύονται, το φαγητό μαγειρεύεται χωρίς σχέδιο και οι ώρες φαρμάκων μετακινούνται. Μια καθημερινή ρουτίνα το αποτρέπει. Το πρωί πρέπει να περιλαμβάνει έλεγχο υγείας, έλεγχο νερού, καθαριότητας, καιρού/ασφάλειας και κατανομή εργασιών. Το βράδυ πρέπει να προετοιμάζεται η νύχτα: πειθαρχία στο φως, προτεραιότητες φόρτισης, δοχεία νερού για αύριο, ασφαλή ρούχα και παπούτσια και έλεγχος ποιος χρειάζεται φάρμακο, ζεστασιά ή ψυχολογική στήριξη. Τα παιδιά χρειάζονται ειλικρινείς αλλά κατάλληλες εξηγήσεις και σταθερές εργασίες. Στην πραγματική χρήση, αυτό δουλεύει καλύτερα όταν επανεξετάζεται αρκετά συχνά ώστε να μένει οικείο κάτω από στρες και αρκετά απλό ώστε να εφαρμόζεται χωρίς δισταγμό. Η πραγματική χρησιμότητα αυξάνεται όταν μια μέθοδος μπορεί να διδαχθεί γρήγορα, να επανεξεταστεί συχνά και να προσαρμοστεί χωρίς να χάσει τη βασική της λογική. Κάτω από στρες, οι άνθρωποι συνήθως επιστρέφουν σε αυτό που είναι οικείο, ορατό και αρκετά απλό ώστε να επαναληφθεί. Η ισχυρότερη γνώση λοιπόν δεν είναι μόνο ακριβής· είναι επίσης οργανωμένη με τρόπο που παραμένει χρήσιμος όταν η μνήμη, ο χρόνος και η υπομονή είναι περιορισμένα. Η ανθρώπινη αξιοπιστία βελτιώνεται όταν οι άνθρωποι ξέρουν τι θα συμβεί μετά, ποιος είναι ο ρόλος τους και πώς θα επανεξετάζονται τα προβλήματα χωρίς ταπείνωση. Μεγάλο μέρος της ανθεκτικότητας είναι ο συναισθηματικός ρυθμός: έλεγχος φημών, μείωση της άσκοπης έκπληξης και εξασφάλιση ότι οι κουρασμένοι άνθρωποι δεν χρειάζεται να λύνουν κάθε πρόβλημα στην κορύφωση του στρες. Η μακροχρόνια ισχύς έρχεται επίσης από το να χρησιμοποιείται το θέμα ως σύστημα και όχι ως ένα μόνο τέχνασμα. Αυτό σημαίνει να ελέγχεται πώς συμπεριφέρεται κάτω από επανάληψη, έλλειψη, κακό καιρό, χαμηλό φως, κόπωση, κίνδυνο μόλυνσης και μεταβίβαση ανάμεσα σε διαφορετικούς ανθρώπους. Η καλύτερη γνώση επιβίωσης μειώνει την υπερφόρτωση αποφάσεων μετατρέποντας τις επαναλαμβανόμενες εργασίες σε ορατές ρουτίνες με καθαρά όρια, σημεία επαναφοράς και εφεδρικές επιλογές. Για το «Family Preparedness and Daily Hardship Routines», το προχωρημένο επίπεδο είναι η αναγνωσιμότητα κάτω από στρες: αν άλλος άνθρωπος μπορεί να καταλάβει, να συνεχίσει και να επαληθεύσει το σύστημα χωρίς να χρειάζεται τον αρχικό συγγραφέα παρόντα. Το βαθύτερο επίπεδο του Family Preparedness and Daily Hardship Routines είναι διαδικαστικό: προετοιμασία, χρονισμός, σημεία αστοχίας, καθάρισμα, παρακολούθηση και όσα ξαναελέγχονται μετά την πρώτη χρήση. Τα συστήματα βελτιώνονται όταν οι μέθοδοι είναι αρκετά καθαρές ώστε να μπορεί να τις επαναλάβει και ένα δεύτερο κουρασμένο άτομο. Ένα σημαντικό επίπεδο στο Family Preparedness and Daily Hardship Routines έρχεται από τη γραφή της μεθόδου έτσι ώστε άλλος κουρασμένος άνθρωπος να μπορεί να την ακολουθήσει μέσα στο σκοτάδι και με περιορισμένη υπομονή. Το Family Preparedness and Daily Hardship Routines γίνεται πιο ανθεκτικό όταν η μέθοδος περιλαμβάνει προετοιμασία, εκτέλεση, έλεγχο, καταγραφή και επαναφορά αντί να θεωρείται τελειωμένη μόλις τελειώσει η ορατή κίνηση. Ένα ακόμη πιο καλοδουλεμένο μάθημα στο Family Preparedness and Daily Hardship Routines είναι η ανθεκτικότητα στη διακοπή. Μια μέθοδος δεν είναι πραγματικά ισχυρή μέχρι να συνεχίζει να δουλεύει μετά από θόρυβο, καθυστέρηση, κουρασμένα χέρια, χαμηλό φως ή αλλαγή προσώπου στη μέση.",
    "steps_en": [
      "Make a one-page daily checklist and keep it visible.",
      "Assign fixed roles but train a backup person for each role.",
      "Keep morning and evening check-ins short, calm, and predictable.",
      "Record medicine use, injuries, water level, and unusual events.",
      "Review the routine weekly and simplify anything that causes friction.",
      "Review the method under calm conditions so it remains usable under pressure.",
      "Use brief predictable check-ins so tension is noticed before it spreads.",
      "Define what counts as success before starting the cycle.",
      "Check the result after one full use cycle and correct the weak part first.",
      "Check what changed after the last full use, not only what happened during the main action.",
      "Note one practical lesson from this cycle so the next repetition starts stronger."
    ],
    "steps_el": [
      "Φτιάξε ένα μονοσέλιδο ημερήσιο checklist και κράτησέ το σε εμφανές σημείο.",
      "Δώσε σταθερούς ρόλους αλλά εκπαίδευσε και δεύτερο άτομο για κάθε ρόλο.",
      "Κράτα τον πρωινό και βραδινό έλεγχο σύντομο, ήρεμο και προβλέψιμο.",
      "Κατέγραψε σε χαρτί φάρμακα, τραυματισμούς, επίπεδο νερού και ασυνήθιστα γεγονότα.",
      "Έλεγξε τη ρουτίνα εβδομαδιαία και απλοποίησε ό,τι δημιουργεί τριβή.",
      "Επανεξέτασε τη μέθοδο σε ήρεμες συνθήκες ώστε να παραμένει χρήσιμη κάτω από πίεση.",
      "Χρησιμοποίησε σύντομα προβλέψιμα check-ins ώστε η ένταση να εντοπίζεται πριν απλωθεί.",
      "Όρισε τι μετρά ως επιτυχία πριν αρχίσει ο κύκλος.",
      "Έλεγξε το αποτέλεσμα μετά από έναν πλήρη κύκλο και διόρθωσε πρώτα το αδύναμο σημείο.",
      "Έλεγξε τι άλλαξε μετά από την τελευταία πλήρη χρήση και όχι μόνο τι συνέβη στη βασική εργασία.",
      "Σημείωσε ένα πρακτικό μάθημα από αυτόν τον κύκλο ώστε η επόμενη επανάληψη να ξεκινήσει ισχυρότερη."
    ],
    "warnings_en": [
      "A routine must adapt to danger, weather, and illness.",
      "Do not overload one competent person until they collapse.",
      "Night preparation is often more important than late-night productivity.",
      "The harder a method is to remember under pressure, the less likely it is to be used correctly.",
      "A method that barely works under ideal conditions may fail completely under fatigue and repeated use.",
      "A routine that works once may still fail later if no one checks how conditions changed."
    ],
    "warnings_el": [
      "Η ρουτίνα πρέπει να προσαρμόζεται σε κίνδυνο, καιρό και ασθένεια.",
      "Μην φορτώνεις ένα ικανό άτομο μέχρι να καταρρεύσει.",
      "Η προετοιμασία της νύχτας είναι συχνά σημαντικότερη από την παραγωγικότητα αργά το βράδυ.",
      "Όσο πιο δύσκολο είναι να θυμηθείς μια μέθοδο κάτω από πίεση, τόσο λιγότερο πιθανό είναι να χρησιμοποιηθεί σωστά.",
      "Μια μέθοδος που μόλις λειτουργεί σε ιδανικές συνθήκες μπορεί να αποτύχει πλήρως κάτω από κόπωση και επαναλαμβανόμενη χρήση.",
      "Μια ρουτίνα που δούλεψε μία φορά μπορεί να αποτύχει αργότερα αν κανείς δεν ελέγξει τι άλλαξε."
    ],
    "mistakes_en": [
      "Turning every day into a crisis meeting.",
      "Hiding all information from children.",
      "Failing to record supplies and medicine because everyone assumes someone else did it.",
      "Adding complexity faster than the method can actually be practiced.",
      "Treating setup as the whole job instead of planning for repeated use and reset.",
      "Repeating a weak process because changing it feels like extra work."
    ],
    "mistakes_el": [
      "Να μετατρέπεις κάθε μέρα σε συμβούλιο κρίσης.",
      "Να κρύβεις τα πάντα από τα παιδιά.",
      "Να μην καταγράφεις προμήθειες και φάρμακα επειδή όλοι νομίζουν ότι το έκανε κάποιος άλλος.",
      "Να προσθέτεις πολυπλοκότητα γρηγορότερα απ’ όσο μπορεί πραγματικά να εξασκηθεί η μέθοδος.",
      "Να αντιμετωπίζεις το στήσιμο ως όλη τη δουλειά αντί να σχεδιάζεις για επαναλαμβανόμενη χρήση και επαναφορά.",
      "Να επαναλαμβάνεις αδύναμη διαδικασία επειδή η αλλαγή μοιάζει με επιπλέον δουλειά."
    ],
    "related_topics": [
      "Survival Priorities Under Pressure",
      "Panic Control and Mental Grounding",
      "Communication Plans and Record Discipline"
    ],
    "difficulty": "low",
    "urgency": "medium",
    "priority": "high",
    "last_updated": "2026-04-02",
    "update_note": "Polish-plus-expansion pass with deeper bilingual detail and broader coverage. Prompt-aligned project restructure and Termux app pass.",
    "topic_en": "Family Preparedness and Daily Hardship Routines"
  }
]